minifold/.gitignore
minifold/__init__.py
minifold/binary_predicate.py
minifold/cache.py
minifold/cached.py
minifold/closure.py
minifold/config.py
minifold/connector.py
minifold/connector_util.py
minifold/count.py
minifold/country.py
minifold/csv.py
minifold/dblp.py
minifold/dict_util.py
minifold/doc_type.py
minifold/download.py
minifold/entries_connector.py
minifold/filesystem.py
minifold/for_each.py
minifold/google_scholar.py
minifold/group_by.py
minifold/hal.py
minifold/hash.py
minifold/html.py
minifold/html_table.py
minifold/ipynb.py
minifold/join_if.py
minifold/json.py
minifold/lambdas.py
minifold/ldap.py
minifold/lexical_cast.py
minifold/limit.py
minifold/log.py
minifold/mongo.py
minifold/natural_join.py
minifold/proxy.py
minifold/query.py
minifold/rename.py
minifold/request_cache.py
minifold/scholar.py
minifold/search.py
minifold/select.py
minifold/singleton.py
minifold/sort_by.py
minifold/strings.py
minifold/twitter.py
minifold/union.py
minifold/unique.py
minifold/unnest.py
minifold/values_from_dict.py
minifold/where.py
minifold-0.10.2.dist-info/LICENSE
minifold-0.10.2.dist-info/WHEEL
minifold-0.10.2.dist-info/METADATA
minifold-0.10.2.dist-info/RECORD
