Metadata-Version: 2.1
Name: minifold
Version: 0.10.2
Summary: Minifold is a Python module able to interact with various data sources (e.g. CSV, LDAP, SQL, twitter, etc.) and to query/combine/aggregate them with database-like operators.
License: BSD-3 license
Author: Marc-Olivier Buob
Author-email: marc-olivier.buob@nokia-bell-labs.com
Requires-Python: >=3.9
Classifier: License :: Other/Proprietary License
Classifier: Programming Language :: Python :: 3
Classifier: Programming Language :: Python :: 3.9
Classifier: Programming Language :: Python :: 3.10
Classifier: Programming Language :: Python :: 3.11
Requires-Dist: beautifulsoup4
Requires-Dist: ldap3
Requires-Dist: lxml (>=5.3.1)
Requires-Dist: pycountry
Requires-Dist: pymongo
Requires-Dist: requests
Requires-Dist: requests-cache
Requires-Dist: tweepy (>=4.15.0)
Requires-Dist: urllib3
Requires-Dist: xmltodict
